<annotation>
	<folder></folder>
	<filename>frame_00372_jpg.rf.c510dd510ee368d5a11b43d82ec83fc1.jpg</filename>
	<path>frame_00372_jpg.rf.c510dd510ee368d5a11b43d82ec83fc1.jpg</path>
	<source>
		<database>roboflow.com</database>
	</source>
	<size>
		<width>300</width>
		<height>300</height>
		<depth>3</depth>
	</size>
	<segmented>0</segmented>
	<object>
		<name>person</name>
		<pose>Unspecified</pose>
		<truncated>0</truncated>
		<difficult>0</difficult>
		<occluded>0</occluded>
		<bndbox>
			<xmin>192</xmin>
			<xmax>199</xmax>
			<ymin>12</ymin>
			<ymax>50</ymax>
		</bndbox>
	</object>
	<object>
		<name>person</name>
		<pose>Unspecified</pose>
		<truncated>0</truncated>
		<difficult>0</difficult>
		<occluded>0</occluded>
		<bndbox>
			<xmin>154</xmin>
			<xmax>161</xmax>
			<ymin>19</ymin>
			<ymax>31</ymax>
		</bndbox>
	</object>
	<object>
		<name>person</name>
		<pose>Unspecified</pose>
		<truncated>0</truncated>
		<difficult>0</difficult>
		<occluded>0</occluded>
		<bndbox>
			<xmin>175</xmin>
			<xmax>181</xmax>
			<ymin>31</ymin>
			<ymax>45</ymax>
		</bndbox>
	</object>
	<object>
		<name>person</name>
		<pose>Unspecified</pose>
		<truncated>0</truncated>
		<difficult>0</difficult>
		<occluded>0</occluded>
		<bndbox>
			<xmin>180</xmin>
			<xmax>188</xmax>
			<ymin>35</ymin>
			<ymax>52</ymax>
		</bndbox>
	</object>
	<object>
		<name>person</name>
		<pose>Unspecified</pose>
		<truncated>0</truncated>
		<difficult>0</difficult>
		<occluded>0</occluded>
		<bndbox>
			<xmin>13</xmin>
			<xmax>33</xmax>
			<ymin>182</ymin>
			<ymax>222</ymax>
		</bndbox>
	</object>
	<object>
		<name>person</name>
		<pose>Unspecified</pose>
		<truncated>0</truncated>
		<difficult>0</difficult>
		<occluded>0</occluded>
		<bndbox>
			<xmin>47</xmin>
			<xmax>54</xmax>
			<ymin>35</ymin>
			<ymax>54</ymax>
		</bndbox>
	</object>
	<metadata>
	</metadata>
</annotation>
